{"v":"5.12.1","fr":60,"ip":0,"op":120,"w":800,"h":600,"nm":"Comp 1","ddd":0,"assets":[],"layers":[{"ddd":0,"ind":1,"ty":4,"nm":"Слой 4/Движение Outlines","sr":1,"ks":{"o":{"a":0,"k":100,"ix":11},"r":{"a":1,"k":[{"i":{"x":[0.833],"y":[0.833]},"o":{"x":[0.167],"y":[0.167]},"t":0,"s":[112.884]},{"i":{"x":[0.833],"y":[0.833]},"o":{"x":[0.167],"y":[0.167]},"t":20,"s":[108.486]},{"i":{"x":[0.833],"y":[0.833]},"o":{"x":[0.167],"y":[0.167]},"t":80,"s":[105.401]},{"t":120,"s":[112.884]}],"ix":10},"p":{"a":1,"k":[{"i":{"x":0.833,"y":0.833},"o":{"x":0.167,"y":0.167},"t":0,"s":[139,262.5,0],"to":[0,0,0],"ti":[0,0,0]},{"i":{"x":0.833,"y":0.833},"o":{"x":0.167,"y":0.167},"t":10,"s":[160,273.5,0],"to":[0,0,0],"ti":[0,0,0]},{"i":{"x":0.833,"y":0.833},"o":{"x":0.167,"y":0.167},"t":20,"s":[231,276.5,0],"to":[0,0,0],"ti":[0,0,0]},{"i":{"x":0.833,"y":0.833},"o":{"x":0.167,"y":0.167},"t":80,"s":[594,287.5,0],"to":[0,0,0],"ti":[0,0,0]},{"i":{"x":0.833,"y":0.833},"o":{"x":0.167,"y":0.167},"t":90,"s":[576,245.5,0],"to":[0,0,0],"ti":[0,0,0]},{"i":{"x":0.833,"y":0.833},"o":{"x":0.167,"y":0.167},"t":110,"s":[249.669,239.833,0],"to":[0,0,0],"ti":[0,0,0]},{"t":120,"s":[139,262.5,0]}],"ix":2,"l":2},"a":{"a":0,"k":[94.5,143.5,0],"ix":1,"l":2},"s":{"a":0,"k":[100,100,100],"ix":6,"l":2}},"ao":0,"shapes":[{"ty":"gr","it":[{"ind":0,"ty":"sh","ix":1,"ks":{"a":0,"k":{"i":[[0,-15.034],[15.034,0],[0,15.034],[-15.035,0]],"o":[[0,15.034],[-15.035,0],[0,-15.034],[15.034,0]],"v":[[27.222,0],[0,27.222],[-27.222,0],[0,-27.222]],"c":true},"ix":2},"nm":"Path 1","mn":"ADBE Vector Shape - Group","hd":false},{"ty":"fl","c":{"a":0,"k":[0.721287087833,0.251680770575,0.247187745337,1],"ix":4},"o":{"a":0,"k":100,"ix":5},"r":1,"bm":0,"nm":"Fill 1","mn":"ADBE Vector Graphic - Fill","hd":false},{"ty":"tr","p":{"a":0,"k":[88.573,46.092],"ix":2},"a":{"a":0,"k":[0,0],"ix":1},"s":{"a":0,"k":[100,100],"ix":3},"r":{"a":0,"k":0,"ix":6},"o":{"a":0,"k":100,"ix":7},"sk":{"a":0,"k":0,"ix":4},"sa":{"a":0,"k":0,"ix":5},"nm":"Transform"}],"nm":"Group 1","np":2,"cix":2,"bm":0,"ix":1,"mn":"ADBE Vector Group","hd":false},{"ty":"gr","it":[{"ind":0,"ty":"sh","ix":1,"ks":{"a":0,"k":{"i":[[0,-20.455],[20.455,0],[0,20.455],[-20.455,0]],"o":[[0,20.455],[-20.455,0],[0,-20.455],[20.455,0]],"v":[[37.037,0],[0,37.037],[-37.037,0],[0,-37.037]],"c":true},"ix":2},"nm":"Path 1","mn":"ADBE Vector Shape - Group","hd":false},{"ty":"fl","c":{"a":0,"k":[0.216866482005,0.219196888045,0.226789048139,1],"ix":4},"o":{"a":0,"k":100,"ix":5},"r":1,"bm":0,"nm":"Fill 1","mn":"ADBE Vector Graphic - Fill","hd":false},{"ty":"tr","p":{"a":0,"k":[88.573,46.684],"ix":2},"a":{"a":0,"k":[0,0],"ix":1},"s":{"a":0,"k":[100,100],"ix":3},"r":{"a":0,"k":0,"ix":6},"o":{"a":0,"k":100,"ix":7},"sk":{"a":0,"k":0,"ix":4},"sa":{"a":0,"k":0,"ix":5},"nm":"Transform"}],"nm":"Group 2","np":2,"cix":2,"bm":0,"ix":2,"mn":"ADBE Vector Group","hd":false},{"ty":"gr","it":[{"ind":0,"ty":"sh","ix":1,"ks":{"a":0,"k":{"i":[[0,0],[5.111,-3.334],[3.513,-8.608],[-0.333,-12.333],[0,0],[0,-4.555],[2.667,-6.889],[1.111,-4.112],[0,0],[1.551,-1.001]],"o":[[0,0],[-5.111,3.333],[-2.222,5.444],[0.333,12.334],[0,0],[0,4.556],[-2.667,6.889],[-1.111,4.111],[0,0],[0,0]],"v":[[20.638,-116.917],[10.526,-106.361],[-10.474,-87.138],[-16.362,-58.695],[-14.585,-16.583],[-10.806,51.305],[-12.474,84.305],[-18.251,102.639],[-19.141,107.527],[-20.638,116.917]],"c":false},"ix":2},"nm":"Path 1","mn":"ADBE Vector Shape - Group","hd":false},{"ty":"st","c":{"a":0,"k":[0.211781101601,0.211387140611,0.207956067254,1],"ix":3},"o":{"a":0,"k":100,"ix":4},"w":{"a":0,"k":1,"ix":5},"lc":1,"lj":1,"ml":10,"bm":0,"nm":"Stroke 1","mn":"ADBE Vector Graphic - Stroke","hd":false},{"ty":"tr","p":{"a":0,"k":[32.898,159.23],"ix":2},"a":{"a":0,"k":[0,0],"ix":1},"s":{"a":0,"k":[100,100],"ix":3},"r":{"a":0,"k":0,"ix":6},"o":{"a":0,"k":100,"ix":7},"sk":{"a":0,"k":0,"ix":4},"sa":{"a":0,"k":0,"ix":5},"nm":"Transform"}],"nm":"Group 3","np":2,"cix":2,"bm":0,"ix":3,"mn":"ADBE Vector Group","hd":false},{"ty":"gr","it":[{"ind":0,"ty":"sh","ix":1,"ks":{"a":0,"k":{"i":[[0,0],[-4.444,3.445],[-6.777,7.334],[0,17.445],[0,0],[5.222,2.889],[0,0],[0.321,-0.361],[0,0]],"o":[[0,0],[4.445,-3.444],[6.778,-7.333],[0,-17.444],[0,0],[-5.222,-2.889],[-1.455,-0.37],[-0.296,0.334],[0,0]],"v":[[-38.444,85.074],[-19,67.407],[26.888,30.518],[38.444,-2.593],[37.112,-68.37],[29.667,-81.259],[22.667,-84.704],[20.434,-84.556],[19.776,-83.933]],"c":false},"ix":2},"nm":"Path 1","mn":"ADBE Vector Shape - Group","hd":false},{"ty":"st","c":{"a":0,"k":[0.182630651137,0.2023912916,0.210072416418,1],"ix":3},"o":{"a":0,"k":100,"ix":4},"w":{"a":0,"k":1,"ix":5},"lc":1,"lj":1,"ml":10,"bm":0,"nm":"Stroke 1","mn":"ADBE Vector Graphic - Stroke","hd":false},{"ty":"tr","p":{"a":0,"k":[55.024,170.129],"ix":2},"a":{"a":0,"k":[0,0],"ix":1},"s":{"a":0,"k":[100,100],"ix":3},"r":{"a":0,"k":0,"ix":6},"o":{"a":0,"k":100,"ix":7},"sk":{"a":0,"k":0,"ix":4},"sa":{"a":0,"k":0,"ix":5},"nm":"Transform"}],"nm":"Group 4","np":2,"cix":2,"bm":0,"ix":4,"mn":"ADBE Vector Group","hd":false},{"ty":"gr","it":[{"ind":0,"ty":"sh","ix":1,"ks":{"a":0,"k":{"i":[[4.148,-5.333],[7.111,-5.63],[0,0],[2.963,3.556],[0.296,10.074],[0,0],[0,0],[-4.148,4.741],[-5.333,-0.889],[-3.794,-4.324],[-0.593,-22.815],[0,0]],"o":[[-4.148,5.333],[-7.111,5.629],[0,0],[-2.963,-3.555],[-0.297,-10.074],[0,0],[0,0],[4.148,-4.741],[5.334,0.889],[3.814,4.347],[0.592,22.814],[0,0]],"v":[[-11.322,33.037],[-25.544,47.852],[-38.581,57.333],[-47.174,57.333],[-50.729,32.741],[-52.211,9.63],[-53.989,-36],[-51.026,-57.926],[-33.841,-69.778],[-15.544,-58.815],[-8.655,-33.333],[-7.47,16.148]],"c":true},"ix":2},"nm":"Path 1","mn":"ADBE Vector Shape - Group","hd":false},{"ind":1,"ty":"sh","ix":2,"ks":{"a":0,"k":{"i":[[0,0],[6.667,-1.333],[0,0],[0,0],[10.576,1.472],[8.148,-2.777],[4,-4],[5.111,-4],[3.556,-6.889],[-0.445,-14.667],[0,0],[0,0],[-7.334,-5.333],[-5.333,0.223],[-4.666,3.334],[-9.778,9.111],[-3.112,13.555],[0.667,24.667],[0,0],[-5.185,2.296],[0,0],[0,0],[0,5.334]],"o":[[0,0],[-6.667,1.334],[0,0],[0,0],[-10.477,-1.459],[-9.035,3.08],[-4,4],[-5.111,4],[-3.555,6.889],[0.444,14.666],[0,0],[0,0],[7.333,5.334],[5.334,-0.222],[4.667,-3.333],[9.778,-9.112],[3.111,-13.556],[-0.666,-24.667],[0,0],[6.506,-2.881],[0,0],[0,0],[0,-5.333]],"v":[[86.456,-131.778],[77.789,-138.445],[32.678,-126.889],[27.122,-125.778],[5.715,-138.148],[-16.433,-136.445],[-36.211,-122.889],[-57.1,-105.556],[-81.1,-83.556],[-90.677,-47.333],[-83.322,90.222],[-82.433,115.555],[-76.655,132.444],[-61.989,139.555],[-46.878,133.555],[11.789,84.667],[36.234,48.889],[40.011,0],[37.419,-85.037],[42.011,-91.333],[77.345,-102],[85.789,-104.445],[91.122,-111.556]],"c":true},"ix":2},"nm":"Path 2","mn":"ADBE Vector Shape - Group","hd":false},{"ty":"mm","mm":1,"nm":"Merge Paths 1","mn":"ADBE Vector Filter - Merge","hd":false},{"ty":"fl","c":{"a":0,"k":[0.286832173665,0.291930404364,0.308147026511,1],"ix":4},"o":{"a":0,"k":100,"ix":5},"r":1,"bm":0,"nm":"Fill 1","mn":"ADBE Vector Graphic - Fill","hd":false},{"ty":"tr","p":{"a":0,"k":[91.372,146.092],"ix":2},"a":{"a":0,"k":[0,0],"ix":1},"s":{"a":0,"k":[100,100],"ix":3},"r":{"a":0,"k":0,"ix":6},"o":{"a":0,"k":100,"ix":7},"sk":{"a":0,"k":0,"ix":4},"sa":{"a":0,"k":0,"ix":5},"nm":"Transform"}],"nm":"Group 8","np":4,"cix":2,"bm":0,"ix":8,"mn":"ADBE Vector Group","hd":false}],"ip":0,"op":122,"st":0,"ct":1,"bm":0},{"ddd":0,"ind":2,"ty":4,"nm":"Слой 5/Движение Outlines","sr":1,"ks":{"o":{"a":0,"k":100,"ix":11},"r":{"a":1,"k":[{"i":{"x":[0.833],"y":[0.833]},"o":{"x":[0.167],"y":[0.167]},"t":0,"s":[115.56]},{"i":{"x":[0.833],"y":[0.833]},"o":{"x":[0.167],"y":[0.167]},"t":20,"s":[108.713]},{"i":{"x":[0.833],"y":[0.833]},"o":{"x":[0.167],"y":[0.167]},"t":80,"s":[107.558]},{"i":{"x":[0.833],"y":[0.833]},"o":{"x":[0.167],"y":[0.167]},"t":110,"s":[113.747]},{"t":119,"s":[115.56]}],"ix":10},"p":{"a":1,"k":[{"i":{"x":0.833,"y":0.833},"o":{"x":0.167,"y":0.167},"t":0,"s":[217,406.5,0],"to":[0,0,0],"ti":[0,0,0]},{"i":{"x":0.833,"y":0.833},"o":{"x":0.167,"y":0.167},"t":10,"s":[242,422,0],"to":[0,0,0],"ti":[0,0,0]},{"i":{"x":0.833,"y":0.833},"o":{"x":0.167,"y":0.167},"t":20,"s":[321,415,0],"to":[0,0,0],"ti":[0,0,0]},{"i":{"x":0.833,"y":0.833},"o":{"x":0.167,"y":0.167},"t":30,"s":[383,421.5,0],"to":[0,0,0],"ti":[0,0,0]},{"i":{"x":0.833,"y":0.833},"o":{"x":0.167,"y":0.167},"t":40,"s":[445,416.5,0],"to":[0,0,0],"ti":[0,0,0]},{"i":{"x":0.833,"y":0.833},"o":{"x":0.167,"y":0.167},"t":50,"s":[506,423.5,0],"to":[0,0,0],"ti":[0,0,0]},{"i":{"x":0.833,"y":0.833},"o":{"x":0.167,"y":0.167},"t":60,"s":[566.5,418,0],"to":[0,0,0],"ti":[0,0,0]},{"i":{"x":0.833,"y":0.833},"o":{"x":0.167,"y":0.167},"t":70,"s":[629,427,0],"to":[0,0,0],"ti":[0,0,0]},{"i":{"x":0.833,"y":0.833},"o":{"x":0.167,"y":0.167},"t":80,"s":[690.5,420,0],"to":[0,0,0],"ti":[0,0,0]},{"i":{"x":0.833,"y":0.833},"o":{"x":0.167,"y":0.167},"t":90,"s":[668,380.5,0],"to":[0,0,0],"ti":[0,0,0]},{"i":{"x":0.833,"y":0.833},"o":{"x":0.167,"y":0.167},"t":100,"s":[502.5,381.5,0],"to":[0,0,0],"ti":[0,0,0]},{"i":{"x":0.833,"y":0.833},"o":{"x":0.167,"y":0.167},"t":110,"s":[333.5,381.5,0],"to":[0,0,0],"ti":[0,0,0]},{"i":{"x":0.833,"y":0.833},"o":{"x":0.167,"y":0.167},"t":119,"s":[229,404.5,0],"to":[0,0,0],"ti":[0,0,0]},{"t":229,"s":[345.5,379.5,0]}],"ix":2,"l":2},"a":{"a":0,"k":[27,19.5,0],"ix":1,"l":2},"s":{"a":0,"k":[100,100,100],"ix":6,"l":2}},"ao":0,"shapes":[{"ty":"gr","it":[{"ind":0,"ty":"sh","ix":1,"ks":{"a":0,"k":{"i":[[-0.474,-0.438],[-2.848,-10.069],[-0.343,-2.955],[0.074,0.639],[6.6,8.41],[2.219,2.049]],"o":[[7.688,7.102],[0.81,2.862],[0.073,0.632],[-1.235,-10.622],[-1.865,-2.377],[-0.472,-0.436]],"v":[[-9.25,-17.785],[6.912,8.614],[8.65,17.356],[9.65,17.356],[-2.406,-11.844],[-8.543,-18.492]],"c":true},"ix":2},"nm":"Path 1","mn":"ADBE Vector Shape - Group","hd":false},{"ind":1,"ty":"sh","ix":2,"ks":{"a":0,"k":{"i":[[0.542,-0.016],[0.888,-1.444],[3.223,-2.334],[2,-2.222],[-1.445,-1.555],[0,0],[0.444,-3.889],[-2.332,-1.555],[-2.988,0.444],[-1.512,-0.356],[-1.246,0.163],[-3.112,3],[-0.778,5.222],[3.778,4.222],[4.01,0]],"o":[[-3.889,0.111],[-0.889,1.444],[-3.222,2.333],[-2,2.223],[1.444,1.556],[0,0],[-0.445,3.889],[2.334,1.555],[1.532,-0.228],[1.436,0.339],[2.555,-0.334],[3.111,-3.001],[0.778,-5.223],[-3.251,-3.634],[-0.649,0]],"v":[[-4.605,-17.966],[-11.604,-13.522],[-19.161,-8.077],[-25.827,-1.856],[-24.715,3.7],[-23.605,7.034],[-23.16,13.367],[-20.161,17.256],[-5.172,18.145],[-0.557,18.63],[3.507,19.145],[11.618,13.034],[16.284,0.923],[10.173,-13.855],[-2.809,-17.995]],"c":true},"ix":2},"nm":"Path 2","mn":"ADBE Vector Shape - Group","hd":false},{"ty":"mm","mm":4,"nm":"Merge Paths 1","mn":"ADBE Vector Filter - Merge","hd":false},{"ty":"fl","c":{"a":0,"k":[0.159261800729,0.159493883918,0.159166657691,1],"ix":4},"o":{"a":0,"k":100,"ix":5},"r":1,"bm":0,"nm":"Fill 1","mn":"ADBE Vector Graphic - Fill","hd":false},{"ty":"tr","p":{"a":0,"k":[36.33,19.178],"ix":2},"a":{"a":0,"k":[0,0],"ix":1},"s":{"a":0,"k":[100,100],"ix":3},"r":{"a":0,"k":0,"ix":6},"o":{"a":0,"k":100,"ix":7},"sk":{"a":0,"k":0,"ix":4},"sa":{"a":0,"k":0,"ix":5},"nm":"Transform"}],"nm":"Group 1","np":4,"cix":2,"bm":0,"ix":1,"mn":"ADBE Vector Group","hd":false},{"ty":"gr","it":[{"ind":0,"ty":"sh","ix":1,"ks":{"a":0,"k":{"i":[[0,0],[1.444,1.555],[-2,2.222],[-3.222,2.333],[-0.889,1.445],[-3.889,0.111],[-3.778,-4.222],[0.778,-5.222],[3.111,-3],[2.556,-0.333],[2.988,-0.444],[2.334,1.556],[-0.444,3.889]],"o":[[0,0],[-1.445,-1.556],[2,-2.222],[3.223,-2.333],[0.889,-1.444],[3.889,-0.111],[3.778,4.222],[-0.778,5.222],[-3.111,3],[-2.555,0.333],[-2.988,0.445],[-2.333,-1.555],[0.445,-3.889]],"v":[[-18.222,6.333],[-19.333,3.001],[-20.445,-2.555],[-13.779,-8.777],[-6.222,-14.223],[0.778,-18.667],[15.555,-14.555],[21.667,0.223],[17,12.333],[8.888,18.445],[0.209,17.445],[-14.779,16.556],[-17.779,12.667]],"c":true},"ix":2},"nm":"Path 1","mn":"ADBE Vector Shape - Group","hd":false},{"ty":"fl","c":{"a":0,"k":[0.223361250933,0.231946264529,0.245871091356,1],"ix":4},"o":{"a":0,"k":100,"ix":5},"r":1,"bm":0,"nm":"Fill 1","mn":"ADBE Vector Graphic - Fill","hd":false},{"ty":"tr","p":{"a":0,"k":[30.947,19.878],"ix":2},"a":{"a":0,"k":[0,0],"ix":1},"s":{"a":0,"k":[100,100],"ix":3},"r":{"a":0,"k":0,"ix":6},"o":{"a":0,"k":100,"ix":7},"sk":{"a":0,"k":0,"ix":4},"sa":{"a":0,"k":0,"ix":5},"nm":"Transform"}],"nm":"Group 2","np":2,"cix":2,"bm":0,"ix":2,"mn":"ADBE Vector Group","hd":false},{"ty":"gr","it":[{"ind":0,"ty":"sh","ix":1,"ks":{"a":0,"k":{"i":[[0,0],[0,0],[0,0],[0,0]],"o":[[0,0],[0,0],[0,0],[0,0]],"v":[[4.561,-7.757],[-8.306,-2.917],[-5.465,7.757],[8.306,4.543]],"c":true},"ix":2},"nm":"Path 1","mn":"ADBE Vector Shape - Group","hd":false},{"ty":"fl","c":{"a":0,"k":[0.69866883521,0.686518889782,0.658356610466,1],"ix":4},"o":{"a":0,"k":100,"ix":5},"r":1,"bm":0,"nm":"Fill 1","mn":"ADBE Vector Graphic - Fill","hd":false},{"ty":"tr","p":{"a":0,"k":[8.556,28.101],"ix":2},"a":{"a":0,"k":[0,0],"ix":1},"s":{"a":0,"k":[100,100],"ix":3},"r":{"a":0,"k":0,"ix":6},"o":{"a":0,"k":100,"ix":7},"sk":{"a":0,"k":0,"ix":4},"sa":{"a":0,"k":0,"ix":5},"nm":"Transform"}],"nm":"Group 3","np":2,"cix":2,"bm":0,"ix":3,"mn":"ADBE Vector Group","hd":false}],"ip":0,"op":122,"st":0,"ct":1,"bm":0},{"ddd":0,"ind":3,"ty":4,"nm":"Слой 2/Движение Outlines","sr":1,"ks":{"o":{"a":0,"k":100,"ix":11},"r":{"a":0,"k":0,"ix":10},"p":{"a":0,"k":[405,477,0],"ix":2,"l":2},"a":{"a":0,"k":[360,56,0],"ix":1,"l":2},"s":{"a":0,"k":[100,100,100],"ix":6,"l":2}},"ao":0,"shapes":[{"ty":"gr","it":[{"ind":0,"ty":"sh","ix":1,"ks":{"a":0,"k":{"i":[[0,0],[24,0],[12.741,1.481],[8,8],[0,18.371],[-10.61,3.838],[-67.259,1.481],[0,0],[0,0],[-26.074,-4.741],[-16,-5.037],[0,-21.416],[4.148,-6.518],[16,-2.667],[58.667,0]],"o":[[0,0],[-24,0],[-12.74,-1.482],[-8,-8],[0,-18.37],[13.926,-5.037],[67.259,-1.482],[0,0],[0,0],[26.074,4.741],[16,5.037],[0,21.416],[-4.149,6.519],[-16,2.667],[-58.667,0]],"v":[[-18.814,55.078],[-187.11,54.947],[-308.296,54.091],[-347.999,41.317],[-359.555,6.354],[-344.444,-26.831],[-200.74,-52.016],[-25.333,-55.572],[150.371,-53.201],[264.148,-46.979],[328.742,-32.757],[359.555,-0.247],[354.815,32.428],[323.408,51.984],[185.333,53.762]],"c":true},"ix":2},"nm":"Path 1","mn":"ADBE Vector Shape - Group","hd":false},{"ty":"fl","c":{"a":0,"k":[0.984593290441,0.813297286688,0.683026422239,1],"ix":4},"o":{"a":0,"k":100,"ix":5},"r":1,"bm":0,"nm":"Fill 1","mn":"ADBE Vector Graphic - Fill","hd":false},{"ty":"tr","p":{"a":0,"k":[359.805,55.822],"ix":2},"a":{"a":0,"k":[0,0],"ix":1},"s":{"a":0,"k":[100,100],"ix":3},"r":{"a":0,"k":0,"ix":6},"o":{"a":0,"k":100,"ix":7},"sk":{"a":0,"k":0,"ix":4},"sa":{"a":0,"k":0,"ix":5},"nm":"Transform"}],"nm":"Group 1","np":2,"cix":2,"bm":0,"ix":1,"mn":"ADBE Vector Group","hd":false}],"ip":0,"op":122,"st":0,"ct":1,"bm":0},{"ddd":0,"ind":4,"ty":4,"nm":"Слой 6/Движение Outlines","sr":1,"ks":{"o":{"a":0,"k":100,"ix":11},"r":{"a":0,"k":0,"ix":10},"p":{"a":0,"k":[425,329,0],"ix":2,"l":2},"a":{"a":0,"k":[283.5,66,0],"ix":1,"l":2},"s":{"a":0,"k":[100,100,100],"ix":6,"l":2}},"ao":0,"hasMask":true,"masksProperties":[{"inv":false,"mode":"a","pt":{"a":1,"k":[{"i":{"x":0.833,"y":0.833},"o":{"x":0.167,"y":0.167},"t":0,"s":[{"i":[[0,0],[0,0],[0,0],[0,0]],"o":[[0,0],[0,0],[0,0],[0,0]],"v":[[-19.5,-75],[-711.5,-75],[-711.5,168],[-19.5,168]],"c":true}]},{"i":{"x":0.833,"y":0.833},"o":{"x":0.167,"y":0.167},"t":14,"s":[{"i":[[0,0],[0,0],[0,0],[0,0]],"o":[[0,0],[0,0],[0,0],[0,0]],"v":[[-19.5,-75],[-711.5,-75],[-711.5,168],[-19.5,168]],"c":true}]},{"i":{"x":0.833,"y":0.833},"o":{"x":0.167,"y":0.167},"t":17,"s":[{"i":[[0,0],[0,0],[0,0],[0,0]],"o":[[0,0],[0,0],[0,0],[0,0]],"v":[[115.5,-75],[-576.5,-75],[-576.5,168],[115.5,168]],"c":true}]},{"i":{"x":0.833,"y":0.833},"o":{"x":0.167,"y":0.167},"t":30,"s":[{"i":[[0,0],[0,0],[0,0],[0,0]],"o":[[0,0],[0,0],[0,0],[0,0]],"v":[[115.5,-75],[-576.5,-75],[-576.5,168],[115.5,168]],"c":true}]},{"i":{"x":0.833,"y":0.833},"o":{"x":0.167,"y":0.167},"t":34,"s":[{"i":[[0,0],[0,0],[0,0],[0,0]],"o":[[0,0],[0,0],[0,0],[0,0]],"v":[[230.5,-75],[-461.5,-75],[-461.5,168],[230.5,168]],"c":true}]},{"i":{"x":0.833,"y":0.833},"o":{"x":0.167,"y":0.167},"t":49,"s":[{"i":[[0,0],[0,0],[0,0],[0,0]],"o":[[0,0],[0,0],[0,0],[0,0]],"v":[[230.5,-75],[-461.5,-75],[-461.5,168],[230.5,168]],"c":true}]},{"i":{"x":0.833,"y":0.833},"o":{"x":0.167,"y":0.167},"t":53,"s":[{"i":[[0,0],[0,0],[0,0],[0,0]],"o":[[0,0],[0,0],[0,0],[0,0]],"v":[[347,-75],[-345,-75],[-345,168],[347,168]],"c":true}]},{"i":{"x":0.833,"y":0.833},"o":{"x":0.167,"y":0.167},"t":64,"s":[{"i":[[0,0],[0,0],[0,0],[0,0]],"o":[[0,0],[0,0],[0,0],[0,0]],"v":[[347,-75],[-345,-75],[-345,168],[347,168]],"c":true}]},{"t":70,"s":[{"i":[[0,0],[0,0],[0,0],[0,0]],"o":[[0,0],[0,0],[0,0],[0,0]],"v":[[568.5,-75],[-123.5,-75],[-123.5,168],[568.5,168]],"c":true}]}],"ix":1},"o":{"a":0,"k":100,"ix":3},"x":{"a":0,"k":0,"ix":4},"nm":"Mask 1"}],"shapes":[{"ty":"gr","it":[{"ind":0,"ty":"sh","ix":1,"ks":{"a":0,"k":{"i":[[4.329,2.357],[0,0],[0,-4.721],[0,0],[-4.146,2.257],[0,0]],"o":[[0,0],[-4.146,-2.258],[0,0],[0,4.721],[0,0],[4.329,-2.357]],"v":[[55.318,-5.465],[-50.449,-63.055],[-59.647,-57.591],[-59.647,57.59],[-50.449,63.055],[55.318,5.464]],"c":true},"ix":2},"nm":"Path 1","mn":"ADBE Vector Shape - Group","hd":false},{"ty":"fl","c":{"a":0,"k":[0.913676243202,0.289791451248,0.330657899146,1],"ix":4},"o":{"a":0,"k":100,"ix":5},"r":1,"bm":0,"nm":"Fill 1","mn":"ADBE Vector Graphic - Fill","hd":false},{"ty":"tr","p":{"a":0,"k":[506.23,65.563],"ix":2},"a":{"a":0,"k":[0,0],"ix":1},"s":{"a":0,"k":[100,100],"ix":3},"r":{"a":0,"k":0,"ix":6},"o":{"a":0,"k":100,"ix":7},"sk":{"a":0,"k":0,"ix":4},"sa":{"a":0,"k":0,"ix":5},"nm":"Transform"}],"nm":"Group 1","np":2,"cix":2,"bm":0,"ix":1,"mn":"ADBE Vector Group","hd":false},{"ty":"gr","it":[{"ind":0,"ty":"sh","ix":1,"ks":{"a":0,"k":{"i":[[2.208,0],[0,0],[0,2.208],[0,0],[-2.208,0],[0,0],[0,-2.208],[0,0]],"o":[[0,0],[-2.208,0],[0,0],[0,-2.208],[0,0],[2.208,0],[0,0],[0,2.208]],"v":[[51.113,41.204],[-51.114,41.204],[-55.111,37.206],[-55.111,-37.206],[-51.114,-41.204],[51.113,-41.204],[55.111,-37.206],[55.111,37.206]],"c":true},"ix":2},"nm":"Path 1","mn":"ADBE Vector Shape - Group","hd":false},{"ty":"fl","c":{"a":0,"k":[0.913676243202,0.289791451248,0.330657899146,1],"ix":4},"o":{"a":0,"k":100,"ix":5},"r":1,"bm":0,"nm":"Fill 1","mn":"ADBE Vector Graphic - Fill","hd":false},{"ty":"tr","p":{"a":0,"k":[404.107,64.83],"ix":2},"a":{"a":0,"k":[0,0],"ix":1},"s":{"a":0,"k":[100,100],"ix":3},"r":{"a":0,"k":0,"ix":6},"o":{"a":0,"k":100,"ix":7},"sk":{"a":0,"k":0,"ix":4},"sa":{"a":0,"k":0,"ix":5},"nm":"Transform"}],"nm":"Group 2","np":2,"cix":2,"bm":0,"ix":2,"mn":"ADBE Vector Group","hd":false},{"ty":"gr","it":[{"ind":0,"ty":"sh","ix":1,"ks":{"a":0,"k":{"i":[[2.207,0],[0,0],[0,2.207],[0,0],[-2.207,0],[0,0],[0,-2.207],[0,0]],"o":[[0,0],[-2.207,0],[0,0],[0,-2.207],[0,0],[2.207,0],[0,0],[0,2.207]],"v":[[51.115,41.204],[-51.115,41.204],[-55.111,37.208],[-55.111,-37.208],[-51.115,-41.204],[51.115,-41.204],[55.111,-37.208],[55.111,37.208]],"c":true},"ix":2},"nm":"Path 1","mn":"ADBE Vector Shape - Group","hd":false},{"ty":"fl","c":{"a":0,"k":[0.913676243202,0.289791451248,0.330657899146,1],"ix":4},"o":{"a":0,"k":100,"ix":5},"r":1,"bm":0,"nm":"Fill 1","mn":"ADBE Vector Graphic - Fill","hd":false},{"ty":"tr","p":{"a":0,"k":[288.757,64.83],"ix":2},"a":{"a":0,"k":[0,0],"ix":1},"s":{"a":0,"k":[100,100],"ix":3},"r":{"a":0,"k":0,"ix":6},"o":{"a":0,"k":100,"ix":7},"sk":{"a":0,"k":0,"ix":4},"sa":{"a":0,"k":0,"ix":5},"nm":"Transform"}],"nm":"Group 3","np":2,"cix":2,"bm":0,"ix":3,"mn":"ADBE Vector Group","hd":false},{"ty":"gr","it":[{"ind":0,"ty":"sh","ix":1,"ks":{"a":0,"k":{"i":[[2.214,0],[0,0],[0,2.214],[0,0],[-2.214,0],[0,0],[0,-2.214],[0,0]],"o":[[0,0],[-2.214,0],[0,0],[0,-2.214],[0,0],[2.214,0],[0,0],[0,2.214]],"v":[[51.102,41.204],[-51.102,41.204],[-55.111,37.195],[-55.111,-37.195],[-51.102,-41.204],[51.102,-41.204],[55.111,-37.195],[55.111,37.195]],"c":true},"ix":2},"nm":"Path 1","mn":"ADBE Vector Shape - Group","hd":false},{"ty":"fl","c":{"a":0,"k":[0.913676243202,0.289791451248,0.330657899146,1],"ix":4},"o":{"a":0,"k":100,"ix":5},"r":1,"bm":0,"nm":"Fill 1","mn":"ADBE Vector Graphic - Fill","hd":false},{"ty":"tr","p":{"a":0,"k":[172.509,64.83],"ix":2},"a":{"a":0,"k":[0,0],"ix":1},"s":{"a":0,"k":[100,100],"ix":3},"r":{"a":0,"k":0,"ix":6},"o":{"a":0,"k":100,"ix":7},"sk":{"a":0,"k":0,"ix":4},"sa":{"a":0,"k":0,"ix":5},"nm":"Transform"}],"nm":"Group 4","np":2,"cix":2,"bm":0,"ix":4,"mn":"ADBE Vector Group","hd":false},{"ty":"gr","it":[{"ind":0,"ty":"sh","ix":1,"ks":{"a":0,"k":{"i":[[2.209,0],[0,0],[0,2.209],[0,0],[-2.209,0],[0,0],[0,-2.21],[0,0]],"o":[[0,0],[-2.209,0],[0,0],[0,-2.21],[0,0],[2.209,0],[0,0],[0,2.209]],"v":[[51.111,41.204],[-51.111,41.204],[-55.111,37.204],[-55.111,-37.204],[-51.111,-41.204],[51.111,-41.204],[55.111,-37.204],[55.111,37.204]],"c":true},"ix":2},"nm":"Path 1","mn":"ADBE Vector Shape - Group","hd":false},{"ty":"fl","c":{"a":0,"k":[0.913676243202,0.289791451248,0.330657899146,1],"ix":4},"o":{"a":0,"k":100,"ix":5},"r":1,"bm":0,"nm":"Fill 1","mn":"ADBE Vector Graphic - Fill","hd":false},{"ty":"tr","p":{"a":0,"k":[55.361,64.83],"ix":2},"a":{"a":0,"k":[0,0],"ix":1},"s":{"a":0,"k":[100,100],"ix":3},"r":{"a":0,"k":0,"ix":6},"o":{"a":0,"k":100,"ix":7},"sk":{"a":0,"k":0,"ix":4},"sa":{"a":0,"k":0,"ix":5},"nm":"Transform"}],"nm":"Group 5","np":2,"cix":2,"bm":0,"ix":5,"mn":"ADBE Vector Group","hd":false}],"ip":0,"op":122,"st":0,"ct":1,"bm":0}],"markers":[],"props":{}}